{
  "id": "ai-analysis-token",
  "symbol": "aiat",
  "name": "AI Analysis Token",
  "image": "https://assets.coingecko.com/coins/images/33672/large/aia-logo-icon200.png?1702702028",
  "current_price": 0.560536,
  "market_cap": 48363174,
  "market_cap_rank": 706,
  "fully_diluted_valuation": 280890818,
  "total_volume": 444388,
  "high_24h": 0.563655,
  "low_24h": 0.530368,
  "price_change_24h": 0.0168075,
  "price_change_percentage_24h": 3.09115,
  "market_cap_change_24h": 1099197,
  "market_cap_change_percentage_24h": 2.32566,
  "circulating_supply": 86088918.6444003,
  "total_supply": 500000000,
  "max_supply": 500000000,
  "ath": 0.571201,
  "ath_change_percentage": -1.60728,
  "ath_date": "2024-04-21T08:19:17.130Z",
  "atl": 0.21982,
  "atl_change_percentage": 155.67241,
  "atl_date": "2024-01-18T23:22:48.788Z",
  "roi": null,
  "last_updated": "2024-04-25T08:59:49.452Z",
  "platforms": {
    "ethereum": "0x0501b9188436e35bb10f35998c40adc079003866"
  }
}