{
  "id": "shita-kiri-suzume",
  "symbol": "suzume",
  "name": "Shita-kiri Suzume",
  "image": "https://assets.coingecko.com/coins/images/26813/large/shitakiri_cmc.png?1696525873",
  "current_price": 3.27892e-7,
  "market_cap": 0,
  "market_cap_rank": null,
  "fully_diluted_valuation": 326361,
  "total_volume": 10835.61,
  "high_24h": 4.25753e-7,
  "low_24h": 3.25034e-7,
  "price_change_24h": -9.579756663e-8,
  "price_change_percentage_24h": -22.61032,
  "market_cap_change_24h": 0,
  "market_cap_change_percentage_24h": 0,
  "circulating_supply": 0,
  "total_supply": 1000000000000,
  "max_supply": 1000000000000,
  "ath": 4.88038e-7,
  "ath_change_percentage": -33.12791,
  "ath_date": "2024-04-23T14:38:45.315Z",
  "atl": 1.78982e-7,
  "atl_change_percentage": 82.34314,
  "atl_date": "2024-04-19T02:31:40.729Z",
  "roi": null,
  "last_updated": "2024-04-25T09:12:42.099Z",
  "platforms": {
    "ethereum": "0x0b452278223d3954f4ac050949d7998e373e7e43"
  }
}