{
  "id": "kendoll-janner",
  "symbol": "ken",
  "name": "Kendoll Janner",
  "image": "https://assets.coingecko.com/coins/images/31260/large/android-chrome-512x512.png?1696530084",
  "current_price": 2.65739e-10,
  "market_cap": 0,
  "market_cap_rank": null,
  "fully_diluted_valuation": 26574,
  "total_volume": 28.66,
  "high_24h": null,
  "low_24h": null,
  "price_change_24h": null,
  "price_change_percentage_24h": null,
  "market_cap_change_24h": null,
  "market_cap_change_percentage_24h": null,
  "circulating_supply": 0,
  "total_supply": 100000000000000,
  "max_supply": 100000000000000,
  "ath": 1.3214e-8,
  "ath_change_percentage": -97.98891,
  "ath_date": "2023-08-15T20:35:30.373Z",
  "atl": 1.948e-10,
  "atl_change_percentage": 36.41583,
  "atl_date": "2023-12-31T02:52:01.696Z",
  "roi": null,
  "last_updated": "2024-04-23T02:49:41.818Z",
  "platforms": {
    "ethereum": "0x2654e753424a9f02df31cfbc6c5af14a87b6cab5"
  }
}