{
  "id": "polkaswap",
  "symbol": "pswap",
  "name": "Polkaswap",
  "image": "https://assets.coingecko.com/coins/images/15475/large/pswap-token-logomark-ticker-icon-200px-transparent-optimized.png?1696515120",
  "current_price": 0.00105071,
  "market_cap": 3768800,
  "market_cap_rank": 1936,
  "fully_diluted_valuation": 10498859,
  "total_volume": 18302.26,
  "high_24h": 0.0011894,
  "low_24h": 0.00098952,
  "price_change_24h": -0.000042573090485276,
  "price_change_percentage_24h": -3.89406,
  "market_cap_change_24h": -160474.86311792303,
  "market_cap_change_percentage_24h": -4.08408,
  "circulating_supply": 3589723365.00698,
  "total_supply": 10000000000,
  "max_supply": 10000000000,
  "ath": 0.880116,
  "ath_change_percentage": -99.87737,
  "ath_date": "2021-05-16T16:04:03.799Z",
  "atl": 0,
  "atl_change_percentage": 1.5672982622123916e+34,
  "atl_date": "2022-05-10T15:21:00.104Z",
  "roi": null,
  "last_updated": "2024-04-25T08:56:44.884Z",
  "platforms": {
    "ethereum": "0x519c1001d550c0a1dae7d1fc220f7d14c2a521bb"
  }
}