{
  "id": "taxa-token",
  "symbol": "txt",
  "name": "Taxa Network",
  "image": "missing_large.png",
  "current_price": 0.00146919,
  "market_cap": 0,
  "market_cap_rank": null,
  "fully_diluted_valuation": 14682721,
  "total_volume": 30089,
  "high_24h": 0.00152126,
  "low_24h": 0.00146449,
  "price_change_24h": -0.000044670794883392,
  "price_change_percentage_24h": -2.95078,
  "market_cap_change_24h": 0,
  "market_cap_change_percentage_24h": 0,
  "circulating_supply": 0,
  "total_supply": 10000000000,
  "max_supply": null,
  "ath": 0.02675211,
  "ath_change_percentage": -94.51767,
  "ath_date": "2021-09-29T12:21:50.300Z",
  "atl": 0.00135101,
  "atl_change_percentage": 8.55825,
  "atl_date": "2023-09-11T14:50:36.987Z",
  "roi": null,
  "last_updated": "2024-04-25T09:16:44.959Z",
  "platforms": {
    "ethereum": "0x547b2f82cecfab9c2b1d36fdda96ef9f58c63b8c"
  }
}