{
  "id": "crypto-hub",
  "symbol": "hub",
  "name": "Crypto Hub",
  "image": "https://assets.coingecko.com/coins/images/32705/large/Untitled_design_%285%29.png?1698985521",
  "current_price": 0.00354088,
  "market_cap": 55722,
  "market_cap_rank": 3960,
  "fully_diluted_valuation": 81440,
  "total_volume": 75.31,
  "high_24h": 0.00354602,
  "low_24h": 0.00350404,
  "price_change_24h": 0.00003684,
  "price_change_percentage_24h": 1.05148,
  "market_cap_change_24h": 466.64,
  "market_cap_change_percentage_24h": 0.84452,
  "circulating_supply": 15736800.281020734,
  "total_supply": 22999999.26461365,
  "max_supply": 100000000,
  "ath": 0.01170233,
  "ath_change_percentage": -69.74207,
  "ath_date": "2023-11-05T19:59:45.906Z",
  "atl": 0.00021732,
  "atl_change_percentage": 1529.36557,
  "atl_date": "2024-02-03T12:04:30.498Z",
  "roi": null,
  "last_updated": "2024-04-24T12:28:41.549Z",
  "platforms": {
    "ethereum": "0x6923f9b683111dcc0e20124e9a031deeae5dad93"
  }
}