{
  "id": "streamr",
  "symbol": "data",
  "name": "Streamr",
  "image": "https://assets.coingecko.com/coins/images/17869/large/DATA_new_symbol_3x.png?1696517392",
  "current_price": 0.062984,
  "market_cap": 48336740,
  "market_cap_rank": 707,
  "fully_diluted_valuation": 63044644,
  "total_volume": 2246675,
  "high_24h": 0.068912,
  "low_24h": 0.062886,
  "price_change_24h": -0.004955423329169901,
  "price_change_percentage_24h": -7.29388,
  "market_cap_change_24h": -3704991.9358723164,
  "market_cap_change_percentage_24h": -7.11927,
  "circulating_supply": 767121867,
  "total_supply": 1000541714,
  "max_supply": 2000000000,
  "ath": 0.209972,
  "ath_change_percentage": -69.93894,
  "ath_date": "2021-12-02T17:13:34.674Z",
  "atl": 0.02014685,
  "atl_change_percentage": 213.29927,
  "atl_date": "2023-09-11T20:10:37.063Z",
  "roi": null,
  "last_updated": "2024-04-25T08:59:50.281Z",
  "platforms": {
    "ethereum": "0x8f693ca8d21b157107184d29d398a8d082b38b76"
  }
}