{
  "id": "flooring-protocol-microsappyseals",
  "symbol": "usaps",
  "name": "FP μSappySeals",
  "image": "https://assets.coingecko.com/coins/images/32787/large/saps_%281%29.png?1699353354",
  "current_price": 0.00210298,
  "market_cap": 136693,
  "market_cap_rank": 3681,
  "fully_diluted_valuation": 136693,
  "total_volume": 4205.95,
  "high_24h": 0.0022158,
  "low_24h": 0.00208966,
  "price_change_24h": -0.000077361604285786,
  "price_change_percentage_24h": -3.54815,
  "market_cap_change_24h": -2882.7301542151254,
  "market_cap_change_percentage_24h": -2.06535,
  "circulating_supply": 65000000,
  "total_supply": 65000000,
  "max_supply": 10000000000,
  "ath": 0.00518804,
  "ath_change_percentage": -59.38628,
  "ath_date": "2024-02-28T05:40:00.003Z",
  "atl": 0.00068722,
  "atl_change_percentage": 206.60374,
  "atl_date": "2023-11-17T16:50:41.608Z",
  "roi": null,
  "last_updated": "2024-04-25T08:48:37.996Z",
  "platforms": {
    "ethereum": "0x97bd0d0a3e9635325ec0b383cff62914a7d50642"
  }
}