{
  "id": "sienna-erc20",
  "symbol": "wsienna",
  "name": "Sienna [ERC-20]",
  "image": "https://assets.coingecko.com/coins/images/15420/large/sienna.jpeg?1696515066",
  "current_price": 0.0265096,
  "market_cap": 0,
  "market_cap_rank": null,
  "fully_diluted_valuation": null,
  "total_volume": 15793.05,
  "high_24h": 0.02800773,
  "low_24h": 0.02385503,
  "price_change_24h": -0.000394259773374789,
  "price_change_percentage_24h": -1.46544,
  "market_cap_change_24h": 0,
  "market_cap_change_percentage_24h": 0,
  "circulating_supply": 0,
  "total_supply": null,
  "max_supply": null,
  "ath": 56.2,
  "ath_change_percentage": -99.95313,
  "ath_date": "2021-10-11T16:19:30.316Z",
  "atl": 0.02385503,
  "atl_change_percentage": 10.42761,
  "atl_date": "2024-04-24T22:50:07.941Z",
  "roi": null,
  "last_updated": "2024-04-25T09:12:41.146Z",
  "platforms": {
    "ethereum": "0x9b00e6e8d787b13756eb919786c9745054db64f9"
  }
}