{
  "id": "staked-ether",
  "symbol": "steth",
  "name": "Lido Staked Ether",
  "image": "https://assets.coingecko.com/coins/images/13442/large/steth_logo.png?1696513206",
  "current_price": 3135.38,
  "market_cap": 29208432186,
  "market_cap_rank": 7,
  "fully_diluted_valuation": 29208432186,
  "total_volume": 113974867,
  "high_24h": 3288.59,
  "low_24h": 3110.99,
  "price_change_24h": -112.96618070924251,
  "price_change_percentage_24h": -3.47766,
  "market_cap_change_24h": -1132226673.0660706,
  "market_cap_change_percentage_24h": -3.73171,
  "circulating_supply": 9343171.34125839,
  "total_supply": 9343171.34125839,
  "max_supply": null,
  "ath": 4829.57,
  "ath_change_percentage": -35.17575,
  "ath_date": "2021-11-10T14:40:47.256Z",
  "atl": 482.9,
  "atl_change_percentage": 548.3242,
  "atl_date": "2020-12-22T04:08:21.854Z",
  "roi": null,
  "last_updated": "2024-04-25T09:02:41.040Z",
  "platforms": {
    "ethereum": "0xae7ab96520de3a18e5e111b5eaab095312d7fe84"
  }
}