{
  "id": "all-coins-yield-capital",
  "symbol": "acyc",
  "name": "All Coins Yield Capital",
  "image": "https://assets.coingecko.com/coins/images/21109/large/acyc.png?1696520489",
  "current_price": 5.06656e-7,
  "market_cap": 0,
  "market_cap_rank": null,
  "fully_diluted_valuation": 506656,
  "total_volume": 16.24,
  "high_24h": 5.1134e-7,
  "low_24h": 5.05338e-7,
  "price_change_24h": -1.30168395e-10,
  "price_change_percentage_24h": -0.02569,
  "market_cap_change_24h": 0,
  "market_cap_change_percentage_24h": 0,
  "circulating_supply": 0,
  "total_supply": 1000000000000,
  "max_supply": 1000000000000,
  "ath": 0.00005388,
  "ath_change_percentage": -99.05963,
  "ath_date": "2021-12-07T23:48:29.635Z",
  "atl": 2.07795e-7,
  "atl_change_percentage": 143.82502,
  "atl_date": "2023-10-25T08:29:19.592Z",
  "roi": null,
  "last_updated": "2024-04-24T14:12:28.409Z",
  "platforms": {
    "ethereum": "0xb56a1f3310578f23120182fb2e58c087efe6e147"
  }
}