{
  "id": "fair-berc20",
  "symbol": "berc",
  "name": "Fair BERC20",
  "image": "https://assets.coingecko.com/coins/images/30860/large/BERClogo3.png_alt_media_token_3c04fa07-9756-4037-8950-e30295030131.png?1696529707",
  "current_price": 0.00259232,
  "market_cap": 0,
  "market_cap_rank": null,
  "fully_diluted_valuation": 54439,
  "total_volume": 16.84,
  "high_24h": null,
  "low_24h": null,
  "price_change_24h": null,
  "price_change_percentage_24h": null,
  "market_cap_change_24h": null,
  "market_cap_change_percentage_24h": null,
  "circulating_supply": 0,
  "total_supply": 21000000,
  "max_supply": 21000000,
  "ath": 0.03145153,
  "ath_change_percentage": -91.75774,
  "ath_date": "2023-07-04T08:46:16.056Z",
  "atl": 0.00155828,
  "atl_change_percentage": 66.35727,
  "atl_date": "2023-10-20T06:11:42.437Z",
  "roi": null,
  "last_updated": "2024-04-22T03:08:08.322Z",
  "platforms": {
    "ethereum": "0xbc8e35221904f61b4200ca44a08e4dac387ac83a"
  }
}