{
  "id": "ecog9coin",
  "symbol": "egc",
  "name": "EcoG9coin",
  "image": "https://assets.coingecko.com/coins/images/8038/large/Screenshot_2019-12-05_at_7.14.34_AM.png?1696508259",
  "current_price": 0.00041906,
  "market_cap": 0,
  "market_cap_rank": null,
  "fully_diluted_valuation": 4190562,
  "total_volume": 4.19,
  "high_24h": null,
  "low_24h": null,
  "price_change_24h": null,
  "price_change_percentage_24h": null,
  "market_cap_change_24h": null,
  "market_cap_change_percentage_24h": null,
  "circulating_supply": 0,
  "total_supply": 10000000000,
  "max_supply": null,
  "ath": 0.050172,
  "ath_change_percentage": -99.16477,
  "ath_date": "2019-04-08T01:00:39.623Z",
  "atl": 0.00005764,
  "atl_change_percentage": 626.97845,
  "atl_date": "2023-08-30T12:43:24.801Z",
  "roi": null,
  "last_updated": "2024-04-23T14:14:16.296Z",
  "platforms": {
    "ethereum": "0xc0ec8caec55f37d47fbfa595727418868a21fd48"
  }
}