{
  "id": "leetcoin",
  "symbol": "leet",
  "name": "LEETCoin",
  "image": "https://assets.coingecko.com/coins/images/32934/large/logo100.png?1699870536",
  "current_price": 0.00000825,
  "market_cap": 0,
  "market_cap_rank": null,
  "fully_diluted_valuation": 11032.26,
  "total_volume": 357.89,
  "high_24h": null,
  "low_24h": null,
  "price_change_24h": null,
  "price_change_percentage_24h": null,
  "market_cap_change_24h": null,
  "market_cap_change_percentage_24h": null,
  "circulating_supply": 0,
  "total_supply": 1337000000,
  "max_supply": 1337000000,
  "ath": 0.00025418,
  "ath_change_percentage": -96.75363,
  "ath_date": "2023-11-13T23:54:33.586Z",
  "atl": 0.00000824,
  "atl_change_percentage": 0.09341,
  "atl_date": "2024-02-26T06:16:28.333Z",
  "roi": null,
  "last_updated": "2024-02-26T06:52:04.615Z",
  "platforms": {
    "ethereum": "0xd6d9f4385bff8670d66a708b258969913619a673"
  }
}