{
  "id": "enigma",
  "symbol": "eng",
  "name": "Enigma",
  "image": "https://assets.coingecko.com/coins/images/1007/large/enigma-logo.png?1696502119",
  "current_price": 0.01656974,
  "market_cap": 1369365,
  "market_cap_rank": 2652,
  "fully_diluted_valuation": 2483196,
  "total_volume": 281740,
  "high_24h": 0.01886514,
  "low_24h": 0.00970375,
  "price_change_24h": 0.00529819,
  "price_change_percentage_24h": 47.005,
  "market_cap_change_24h": 269065,
  "market_cap_change_percentage_24h": 24.45376,
  "circulating_supply": 82717911.64,
  "total_supply": 150000000,
  "max_supply": null,
  "ath": 8.19,
  "ath_change_percentage": -99.79788,
  "ath_date": "2018-01-10T00:00:00.000Z",
  "atl": 0.00150568,
  "atl_change_percentage": 999.47902,
  "atl_date": "2023-11-25T11:40:41.382Z",
  "roi": null,
  "last_updated": "2024-04-25T09:02:54.261Z",
  "platforms": {
    "ethereum": "0xf0ee6b27b759c9893ce4f094b49ad28fd15a23e4"
  }
}