{
  "id": "holoride",
  "symbol": "ride",
  "name": "holoride",
  "image": "https://assets.coingecko.com/coins/images/21626/large/RIDE_Token_Symbol_MASTER.png?1696520986",
  "current_price": 0.01088006,
  "market_cap": 9296790,
  "market_cap_rank": 1468,
  "fully_diluted_valuation": 10873106,
  "total_volume": 93348,
  "high_24h": 0.01163136,
  "low_24h": 0.01022436,
  "price_change_24h": -0.000628982817370739,
  "price_change_percentage_24h": -5.46512,
  "market_cap_change_24h": -413433.889807947,
  "market_cap_change_percentage_24h": -4.25772,
  "circulating_supply": 854850323,
  "total_supply": 999794371,
  "max_supply": 1000000000,
  "ath": 2.5,
  "ath_change_percentage": -99.56589,
  "ath_date": "2021-12-23T19:52:37.120Z",
  "atl": 0.00920705,
  "atl_change_percentage": 18.08087,
  "atl_date": "2023-10-14T16:25:54.577Z",
  "roi": null,
  "last_updated": "2024-04-25T08:59:52.437Z",
  "platforms": {
    "ethereum": "0xf97e2a78f1f3d1fd438ff7cc3bb7de01e5945b83"
  }
}