{
  "id": "neptune-mutual",
  "symbol": "npm",
  "name": "Neptune Mutual",
  "image": "https://assets.coingecko.com/coins/images/28235/large/Neptune_Mutual_Logo_Icon_Regular_128.png?1696527238",
  "current_price": 0.03235587,
  "market_cap": 2853489,
  "market_cap_rank": 2090,
  "fully_diluted_valuation": 3348627,
  "total_volume": 17804.85,
  "high_24h": 0.03256278,
  "low_24h": 0.03155409,
  "price_change_24h": 0.00059421,
  "price_change_percentage_24h": 1.87084,
  "market_cap_change_24h": -5139.383290925063,
  "market_cap_change_percentage_24h": -0.17978,
  "circulating_supply": 88265158.661955,
  "total_supply": 103580952.36,
  "max_supply": 1000000000,
  "ath": 0.04216759,
  "ath_change_percentage": -24.93273,
  "ath_date": "2023-12-15T20:05:11.190Z",
  "atl": 0.03152171,
  "atl_change_percentage": 0.41986,
  "atl_date": "2023-12-28T08:41:44.053Z",
  "roi": null,
  "last_updated": "2024-04-25T08:54:35.866Z",
  "platforms": {
    "arbitrum": "0x57f12fe6a4e5fe819eec699fadf9db2d06606bb4"
  }
}