{
  "id": "gnome",
  "symbol": "$gnome",
  "name": "GNOME",
  "image": "https://assets.coingecko.com/coins/images/20885/large/gnome.png?1696520278",
  "current_price": 0.112479,
  "market_cap": 0,
  "market_cap_rank": null,
  "fully_diluted_valuation": 1124785,
  "total_volume": 344.24,
  "high_24h": 0.11675,
  "low_24h": 0.111345,
  "price_change_24h": -0.004271791609889289,
  "price_change_percentage_24h": -3.65891,
  "market_cap_change_24h": 0,
  "market_cap_change_percentage_24h": 0,
  "circulating_supply": 0,
  "total_supply": 10000000,
  "max_supply": 10000000,
  "ath": 2.22,
  "ath_change_percentage": -94.94257,
  "ath_date": "2021-11-25T16:51:09.465Z",
  "atl": 0.00732127,
  "atl_change_percentage": 1436.32624,
  "atl_date": "2022-08-05T20:39:48.234Z",
  "roi": null,
  "last_updated": "2024-04-25T05:46:15.518Z",
  "platforms": {
    "arbitrum": "0x7698ac5d15bb3ba7185adcbff32a80ebd9d0709b"
  }
}