{
  "id": "finance-vote",
  "symbol": "fvt",
  "name": "Finance Vote",
  "image": "https://assets.coingecko.com/coins/images/13181/large/finance.png?1696512964",
  "current_price": 0.00048277,
  "market_cap": 98830,
  "market_cap_rank": 3786,
  "fully_diluted_valuation": 478141,
  "total_volume": 5.26,
  "high_24h": null,
  "low_24h": null,
  "price_change_24h": null,
  "price_change_percentage_24h": null,
  "market_cap_change_24h": null,
  "market_cap_change_percentage_24h": null,
  "circulating_supply": 204714180.7344784,
  "total_supply": 990414451.13739,
  "max_supply": null,
  "ath": 0.093714,
  "ath_change_percentage": -99.48485,
  "ath_date": "2021-03-20T16:25:33.577Z",
  "atl": 0.00034491,
  "atl_change_percentage": 39.97134,
  "atl_date": "2023-09-27T15:40:41.524Z",
  "roi": null,
  "last_updated": "2024-04-22T01:00:20.492Z",
  "platforms": {
    "bsc": "0x0a232cb2005bda62d3de7ab5deb3ffe4c456165a"
  }
}