{
  "id": "jarvis-synthetic-euro",
  "symbol": "jeur",
  "name": "Jarvis Synthetic Euro",
  "image": "https://assets.coingecko.com/coins/images/15725/large/jEUR.png?1696515352",
  "current_price": 0.977732,
  "market_cap": 0,
  "market_cap_rank": null,
  "fully_diluted_valuation": 620679,
  "total_volume": 636.31,
  "high_24h": 0.99116,
  "low_24h": 0.971118,
  "price_change_24h": -0.004112958853051852,
  "price_change_percentage_24h": -0.4189,
  "market_cap_change_24h": 0,
  "market_cap_change_percentage_24h": 0,
  "circulating_supply": 0,
  "total_supply": 635307,
  "max_supply": null,
  "ath": 4.01,
  "ath_change_percentage": -75.58686,
  "ath_date": "2021-11-06T08:13:28.752Z",
  "atl": 0.857372,
  "atl_change_percentage": 14.20666,
  "atl_date": "2022-11-10T11:25:18.827Z",
  "roi": null,
  "last_updated": "2024-04-25T09:04:42.918Z",
  "platforms": {
    "bsc": "0x23b8683ff98f9e4781552dfe6f12aa32814924e8"
  }
}