{
  "id": "jade-currency",
  "symbol": "jade",
  "name": "Jade Currency",
  "image": "https://assets.coingecko.com/coins/images/10072/large/photo_2021-05-31_15.02.34.jpeg?1696510103",
  "current_price": 0.00141971,
  "market_cap": 83236,
  "market_cap_rank": 3840,
  "fully_diluted_valuation": 127897,
  "total_volume": 4.79,
  "high_24h": 0.00144925,
  "low_24h": 0.00138809,
  "price_change_24h": -0.000007655183279721,
  "price_change_percentage_24h": -0.53632,
  "market_cap_change_24h": -425.641159949344,
  "market_cap_change_percentage_24h": -0.50877,
  "circulating_supply": 58572217.337,
  "total_supply": 90000000,
  "max_supply": 90000000,
  "ath": 0.47931,
  "ath_change_percentage": -99.70486,
  "ath_date": "2021-08-22T12:51:13.169Z",
  "atl": 0.0000937,
  "atl_change_percentage": 1409.75477,
  "atl_date": "2020-06-17T16:57:13.609Z",
  "roi": null,
  "last_updated": "2024-04-25T08:59:45.845Z",
  "platforms": {
    "bsc": "0x330f4fe5ef44b4d0742fe8bed8ca5e29359870df"
  }
}