{
  "id": "dodo",
  "symbol": "dodo",
  "name": "DODO",
  "image": "https://assets.coingecko.com/coins/images/12651/large/dodo_logo.png?1696512458",
  "current_price": 0.180927,
  "market_cap": 118520659,
  "market_cap_rank": 422,
  "fully_diluted_valuation": 180028477,
  "total_volume": 24639438,
  "high_24h": 0.217232,
  "low_24h": 0.180517,
  "price_change_24h": -0.020046530411076652,
  "price_change_percentage_24h": -9.9747,
  "market_cap_change_24h": -13241830.879258215,
  "market_cap_change_percentage_24h": -10.04977,
  "circulating_supply": 655703404.35,
  "total_supply": 995989104.366833,
  "max_supply": 1000000000,
  "ath": 8.38,
  "ath_change_percentage": -97.84432,
  "ath_date": "2021-02-20T09:19:28.624Z",
  "atl": 0.080974,
  "atl_change_percentage": 123.01087,
  "atl_date": "2023-06-10T14:15:17.108Z",
  "roi": null,
  "last_updated": "2024-04-25T08:56:07.991Z",
  "platforms": {
    "bsc": "0x67ee3cb086f8a16f34bee3ca72fad36f7db929e2"
  }
}