{
  "id": "staysafu",
  "symbol": "safu",
  "name": "StaySAFU",
  "image": "https://assets.coingecko.com/coins/images/17781/large/staysafu.PNG?1696517305",
  "current_price": 3.27,
  "market_cap": 54493,
  "market_cap_rank": 3966,
  "fully_diluted_valuation": 62663,
  "total_volume": 11.36,
  "high_24h": 3.27,
  "low_24h": 3.27,
  "price_change_24h": 0.00372191,
  "price_change_percentage_24h": 0.11393,
  "market_cap_change_24h": -57.251464466011385,
  "market_cap_change_percentage_24h": -0.10495,
  "circulating_supply": 16661.064754587,
  "total_supply": 19159,
  "max_supply": 20000,
  "ath": 74.19,
  "ath_change_percentage": -95.59132,
  "ath_date": "2021-11-23T06:49:14.506Z",
  "atl": 0.97278,
  "atl_change_percentage": 236.22088,
  "atl_date": "2022-06-04T18:55:30.208Z",
  "roi": null,
  "last_updated": "2024-04-24T09:25:58.519Z",
  "platforms": {
    "bsc": "0x890cc7d14948478c98a6cd7f511e1f7f7f99f397"
  }
}