{
  "id": "social-capitalism-2",
  "symbol": "socap",
  "name": "Social Capitalism",
  "image": "https://assets.coingecko.com/coins/images/26083/large/oPT2utjj_400x400.png?1696525174",
  "current_price": 5.59,
  "market_cap": 0,
  "market_cap_rank": null,
  "fully_diluted_valuation": 838101659,
  "total_volume": 2011.44,
  "high_24h": null,
  "low_24h": null,
  "price_change_24h": null,
  "price_change_percentage_24h": null,
  "market_cap_change_24h": null,
  "market_cap_change_percentage_24h": null,
  "circulating_supply": 0,
  "total_supply": 150000000,
  "max_supply": 150000000,
  "ath": 30.07,
  "ath_change_percentage": -81.41643,
  "ath_date": "2022-10-16T20:42:24.660Z",
  "atl": 0.907492,
  "atl_change_percentage": 515.69106,
  "atl_date": "2022-06-22T09:13:55.215Z",
  "roi": null,
  "last_updated": "2024-04-23T18:14:56.109Z",
  "platforms": {
    "bsc": "0xb4ebc6fd70a852d052163f25949c70fb9506d6a0"
  }
}