{
  "id": "horizon-protocol",
  "symbol": "hzn",
  "name": "Horizon Protocol",
  "image": "https://assets.coingecko.com/coins/images/14795/large/HZN_logo_drak2.png?1708723124",
  "current_price": 0.03841802,
  "market_cap": 6202568,
  "market_cap_rank": 1690,
  "fully_diluted_valuation": 9218171,
  "total_volume": 75039,
  "high_24h": 0.04126581,
  "low_24h": 0.03838378,
  "price_change_24h": -0.002473868150703655,
  "price_change_percentage_24h": -6.04978,
  "market_cap_change_24h": -401084.97850256413,
  "market_cap_change_percentage_24h": -6.07368,
  "circulating_supply": 161593472.82114,
  "total_supply": 240157969.500456,
  "max_supply": 240157969.500456,
  "ath": 1.62,
  "ath_change_percentage": -97.62623,
  "ath_date": "2021-04-15T00:00:00.000Z",
  "atl": 0.01539238,
  "atl_change_percentage": 150.06018,
  "atl_date": "2023-10-26T14:40:31.964Z",
  "roi": null,
  "last_updated": "2024-04-25T08:59:44.838Z",
  "platforms": {
    "bsc": "0xc0eff7749b125444953ef89682201fb8c6a917cd"
  }
}