{
  "id": "hedgepay",
  "symbol": "hpay",
  "name": "HedgePay",
  "image": "https://assets.coingecko.com/coins/images/27725/large/200x200CG.png?1696526749",
  "current_price": 0.00039927,
  "market_cap": 48082,
  "market_cap_rank": 3999,
  "fully_diluted_valuation": 47125,
  "total_volume": 0.83338,
  "high_24h": null,
  "low_24h": null,
  "price_change_24h": null,
  "price_change_percentage_24h": null,
  "market_cap_change_24h": null,
  "market_cap_change_percentage_24h": null,
  "circulating_supply": 120424719.347,
  "total_supply": 118026856,
  "max_supply": 1000000000,
  "ath": 0.00201876,
  "ath_change_percentage": -80.22189,
  "ath_date": "2022-10-14T01:57:43.826Z",
  "atl": 0.00038904,
  "atl_change_percentage": 2.63076,
  "atl_date": "2023-07-10T08:56:17.518Z",
  "roi": null,
  "last_updated": "2023-08-03T10:42:32.956Z",
  "platforms": {
    "bsc": "0xc75aa1fa199eac5adabc832ea4522cff6dfd521a"
  }
}