{
  "id": "2024pump",
  "symbol": "pump",
  "name": "2024PUMP",
  "image": "https://assets.coingecko.com/coins/images/33052/large/200x200_2024_logo.png?1700474858",
  "current_price": 0.00000189,
  "market_cap": 0,
  "market_cap_rank": null,
  "fully_diluted_valuation": 3828941680,
  "total_volume": 117948,
  "high_24h": 0.00000234,
  "low_24h": 0.00000183,
  "price_change_24h": -4.52984058241e-7,
  "price_change_percentage_24h": -19.32061,
  "market_cap_change_24h": 0,
  "market_cap_change_percentage_24h": 0,
  "circulating_supply": 0,
  "total_supply": 2024202420242024,
  "max_supply": 2024202420242024,
  "ath": 0.02061351,
  "ath_change_percentage": -99.99082,
  "ath_date": "2023-11-20T10:42:01.897Z",
  "atl": 0.00000183,
  "atl_change_percentage": 3.38648,
  "atl_date": "2024-04-25T08:26:35.211Z",
  "roi": null,
  "last_updated": "2024-04-25T09:13:28.407Z",
  "platforms": {
    "bsc": "0xcee4e6f4d8e634e329c457a4f98c090afafb1c4b"
  }
}