{
  "id": "bullshits404",
  "symbol": "bs",
  "name": "Bullshits404",
  "image": "https://assets.coingecko.com/coins/images/35163/large/bullshits404_logo.png?1707662597",
  "current_price": 17.68,
  "market_cap": 0,
  "market_cap_rank": null,
  "fully_diluted_valuation": 176804,
  "total_volume": 19.91,
  "high_24h": 18,
  "low_24h": 17.41,
  "price_change_24h": -0.0384686139621877,
  "price_change_percentage_24h": -0.2171,
  "market_cap_change_24h": 0,
  "market_cap_change_percentage_24h": 0,
  "circulating_supply": 0,
  "total_supply": 10000,
  "max_supply": 10000,
  "ath": 49.82,
  "ath_change_percentage": -64.50894,
  "ath_date": "2024-02-11T15:49:41.119Z",
  "atl": 10.43,
  "atl_change_percentage": 69.58609,
  "atl_date": "2024-02-29T14:53:49.367Z",
  "roi": null,
  "last_updated": "2024-04-25T04:43:25.213Z",
  "platforms": {
    "bsc": "0xdec515489e4a12b9429a976b18a1a7459c148891"
  }
}