{
  "id": "wolfsafepoorpeople-polygon",
  "symbol": "wspp",
  "name": "WolfSafePoorPeople Polygon",
  "image": "https://assets.coingecko.com/coins/images/19514/large/wspplogo.png?1696518948",
  "current_price": 9.996e-9,
  "market_cap": 15.83,
  "market_cap_rank": 4301,
  "fully_diluted_valuation": 12.14,
  "total_volume": 0.03969864,
  "high_24h": 2.0021e-8,
  "low_24h": 9.956e-9,
  "price_change_24h": -1.0005633101e-8,
  "price_change_percentage_24h": -50.02306,
  "market_cap_change_24h": -15.790571860778938,
  "market_cap_change_percentage_24h": -49.93021,
  "circulating_supply": 1584040062,
  "total_supply": 1214040062,
  "max_supply": 1214040062,
  "ath": 0.00131156,
  "ath_change_percentage": -99.99924,
  "ath_date": "2021-10-27T13:45:17.218Z",
  "atl": 2.00014e-10,
  "atl_change_percentage": 4897.84951,
  "atl_date": "2023-11-15T10:39:34.406Z",
  "roi": null,
  "last_updated": "2024-04-25T08:56:07.020Z",
  "platforms": {
    "polygon": "0x46d502fac9aea7c5bc7b13c8ec9d02378c33d36f"
  }
}