{
  "id": "havven",
  "symbol": "snx",
  "name": "Synthetix Network",
  "image": "https://assets.coingecko.com/coins/images/3406/large/SNX.png?1696504103",
  "current_price": 2.81,
  "market_cap": 920015533,
  "market_cap_rank": 105,
  "fully_diluted_valuation": 921205401,
  "total_volume": 35432982,
  "high_24h": 3.12,
  "low_24h": 2.78,
  "price_change_24h": -0.25741345687626405,
  "price_change_percentage_24h": -8.40162,
  "market_cap_change_24h": -87862931.6549877,
  "market_cap_change_percentage_24h": -8.71761,
  "circulating_supply": 327769196.13952357,
  "total_supply": 328193104.088774,
  "max_supply": 328193104.088774,
  "ath": 28.53,
  "ath_change_percentage": -90.16145,
  "ath_date": "2021-02-14T01:12:38.505Z",
  "atl": 0.0347864,
  "atl_change_percentage": 7969.71212,
  "atl_date": "2019-01-06T00:00:00.000Z",
  "roi": {
    "times": 4.612881832893874,
    "currency": "usd",
    "percentage": 461.2881832893874
  },
  "last_updated": "2024-04-25T09:02:47.094Z",
  "platforms": {
    "polygon": "0x50b728d8d964fd00c2d0aad81718b71311fef68a"
  }
}